termitype/__init__.py
termitype/__main__.py
termitype/adapters/__init__.py
termitype/adapters/base.py
termitype/adapters/linux.py
termitype/adapters/macos.py
termitype/adapters/windows.py
termitype/app/__init__.py
termitype/app/app.py
termitype/app/context.py
termitype/cli/__init__.py
termitype/cli/bootstrap.py
termitype/cli/shutdown.py
termitype/core/__init__.py
termitype/core/engine.py
termitype/models/__init__.py
termitype/models/inputevent.py
termitype/models/settings.py
termitype/models/engine/__init__.py
termitype/models/engine/run.py
termitype/models/engine/runreport.py
termitype/models/presentation/__init__.py
termitype/models/presentation/cursor.py
termitype/models/presentation/highlight.py
termitype/models/presentation/presentation.py
termitype/screens/__init__.py
termitype/screens/base.py
termitype/screens/dashboard.py
termitype/screens/settings.py
termitype/screens/typingrun.py
termitype/static/settings.json
termitype/static/languages/english.json
termitype/storage/__init__.py
termitype/storage/paths.py
termitype/storage/storagemanager.py
termitype/utils/__init__.py
termitype/utils/color.py
termitype/utils/visuals.py
termitype/utils/words.py
termitype-0.5.0.dist-info/licenses/LICENSE
termitype-0.5.0.dist-info/METADATA
termitype-0.5.0.dist-info/WHEEL
termitype-0.5.0.dist-info/entry_points.txt
termitype-0.5.0.dist-info/top_level.txt
termitype-0.5.0.dist-info/RECORD
