Metadata-Version: 2.4
Name: termitype
Version: 0.5.0
Summary: A minimalist terminal typing speed test.
Author: sawsent
License: Copyright 2025 sawsent
Project-URL: Homepage, https://github.com/sawsent/termitype
Project-URL: Source, https://github.com/sawsent/termitype
Classifier: License :: OSI Approved :: Apache Software License
Requires-Python: >=3.9
License-File: LICENSE
Requires-Dist: platformdirs>=3.0.0
Dynamic: license-file
